{
  "aggregated": {
    "community": "UVA-C",
    "P_max": 7000,
    "H_max": 5,
    "panic_rate": 0.1,
    "n_seeds": 10,
    "hazard_seed": 1135,
    "RI": 0.18810000000000002,
    "RI_std": 0.02750302766264552,
    "RS": 0.12787733534243287,
    "RS_std": 0.03284440950446812,
    "RC": 0.10738422440378954,
    "RC_std": 0.007457439825241609,
    "RL": 0.7647384402537776,
    "RL_std": 0.030486852875111537,
    "elapsed_sec": 186.00000000000003
  },
  "raw": [
    {
      "P_max": 7000,
      "n_impacted": 1536,
      "n_survival": 168,
      "n_casualty": 172,
      "n_arrival": 5464,
      "n_active": 1196,
      "RI": 0.21942857142857142,
      "RS": 0.109375,
      "RC": 0.11197916666666667,
      "RL": 0.7786458333333334,
      "community": "UVA-C",
      "H_max": 5,
      "panic_rate": 0.1,
      "seed": 42,
      "hazard_seed": 1135,
      "elapsed_sec": 19.6
    },
    {
      "P_max": 7000,
      "n_impacted": 1247,
      "n_survival": 145,
      "n_casualty": 130,
      "n_arrival": 5753,
      "n_active": 972,
      "RI": 0.17814285714285713,
      "RS": 0.11627906976744186,
      "RC": 0.10425020048115477,
      "RL": 0.7794707297514034,
      "community": "UVA-C",
      "H_max": 5,
      "panic_rate": 0.1,
      "seed": 142,
      "hazard_seed": 1135,
      "elapsed_sec": 12.1
    },
    {
      "P_max": 7000,
      "n_impacted": 919,
      "n_survival": 174,
      "n_casualty": 96,
      "n_arrival": 6081,
      "n_active": 649,
      "RI": 0.13128571428571428,
      "RS": 0.1893362350380849,
      "RC": 0.1044613710554951,
      "RL": 0.70620239390642,
      "community": "UVA-C",
      "H_max": 5,
      "panic_rate": 0.1,
      "seed": 242,
      "hazard_seed": 1135,
      "elapsed_sec": 18.8
    },
    {
      "P_max": 7000,
      "n_impacted": 1485,
      "n_survival": 118,
      "n_casualty": 156,
      "n_arrival": 5515,
      "n_active": 1211,
      "RI": 0.21214285714285713,
      "RS": 0.07946127946127945,
      "RC": 0.10505050505050505,
      "RL": 0.8154882154882155,
      "community": "UVA-C",
      "H_max": 5,
      "panic_rate": 0.1,
      "seed": 342,
      "hazard_seed": 1135,
      "elapsed_sec": 21.2
    },
    {
      "P_max": 7000,
      "n_impacted": 1226,
      "n_survival": 170,
      "n_casualty": 140,
      "n_arrival": 5774,
      "n_active": 916,
      "RI": 0.17514285714285716,
      "RS": 0.13866231647634583,
      "RC": 0.11419249592169657,
      "RL": 0.7471451876019576,
      "community": "UVA-C",
      "H_max": 5,
      "panic_rate": 0.1,
      "seed": 442,
      "hazard_seed": 1135,
      "elapsed_sec": 19.5
    },
    {
      "P_max": 7000,
      "n_impacted": 1310,
      "n_survival": 163,
      "n_casualty": 125,
      "n_arrival": 5690,
      "n_active": 1022,
      "RI": 0.18714285714285714,
      "RS": 0.12442748091603054,
      "RC": 0.09541984732824428,
      "RL": 0.7801526717557252,
      "community": "UVA-C",
      "H_max": 5,
      "panic_rate": 0.1,
      "seed": 542,
      "hazard_seed": 1135,
      "elapsed_sec": 20.1
    },
    {
      "P_max": 7000,
      "n_impacted": 1586,
      "n_survival": 144,
      "n_casualty": 185,
      "n_arrival": 5414,
      "n_active": 1257,
      "RI": 0.22657142857142856,
      "RS": 0.09079445145018916,
      "RC": 0.11664564943253468,
      "RL": 0.7925598991172762,
      "community": "UVA-C",
      "H_max": 5,
      "panic_rate": 0.1,
      "seed": 642,
      "hazard_seed": 1135,
      "elapsed_sec": 21.3
    },
    {
      "P_max": 7000,
      "n_impacted": 1137,
      "n_survival": 204,
      "n_casualty": 108,
      "n_arrival": 5863,
      "n_active": 825,
      "RI": 0.16242857142857142,
      "RS": 0.17941952506596306,
      "RC": 0.09498680738786279,
      "RL": 0.7255936675461742,
      "community": "UVA-C",
      "H_max": 5,
      "panic_rate": 0.1,
      "seed": 742,
      "hazard_seed": 1135,
      "elapsed_sec": 19.5
    },
    {
      "P_max": 7000,
      "n_impacted": 1445,
      "n_survival": 177,
      "n_casualty": 167,
      "n_arrival": 5555,
      "n_active": 1101,
      "RI": 0.20642857142857143,
      "RS": 0.12249134948096886,
      "RC": 0.11557093425605536,
      "RL": 0.7619377162629758,
      "community": "UVA-C",
      "H_max": 5,
      "panic_rate": 0.1,
      "seed": 842,
      "hazard_seed": 1135,
      "elapsed_sec": 20.5
    },
    {
      "P_max": 7000,
      "n_impacted": 1276,
      "n_survival": 164,
      "n_casualty": 142,
      "n_arrival": 5724,
      "n_active": 970,
      "RI": 0.18228571428571427,
      "RS": 0.12852664576802508,
      "RC": 0.11128526645768025,
      "RL": 0.7601880877742947,
      "community": "UVA-C",
      "H_max": 5,
      "panic_rate": 0.1,
      "seed": 942,
      "hazard_seed": 1135,
      "elapsed_sec": 13.4
    }
  ]
}