{
  "aggregated": {
    "community": "UVA-C",
    "P_max": 13000,
    "H_max": 15,
    "panic_rate": 0.1,
    "n_seeds": 10,
    "hazard_seed": 1135,
    "RI": 0.776876923076923,
    "RI_std": 0.006000907229241616,
    "RS": 0.4725673965946666,
    "RS_std": 0.017407084463138305,
    "RC": 0.07360218459664165,
    "RC_std": 0.003911778706591351,
    "RL": 0.4538304188086917,
    "RL_std": 0.014375731488392848,
    "elapsed_sec": 195.0
  },
  "raw": [
    {
      "P_max": 13000,
      "n_impacted": 10131,
      "n_survival": 4459,
      "n_casualty": 795,
      "n_arrival": 2869,
      "n_active": 4877,
      "RI": 0.7793076923076923,
      "RS": 0.44013424143717306,
      "RC": 0.07847201658276577,
      "RL": 0.4813937419800612,
      "community": "UVA-C",
      "H_max": 15,
      "panic_rate": 0.1,
      "seed": 42,
      "hazard_seed": 1135,
      "elapsed_sec": 20.3
    },
    {
      "P_max": 13000,
      "n_impacted": 10081,
      "n_survival": 4710,
      "n_casualty": 773,
      "n_arrival": 2919,
      "n_active": 4598,
      "RI": 0.7754615384615384,
      "RS": 0.46721555401249876,
      "RC": 0.07667890090268822,
      "RL": 0.456105545084813,
      "community": "UVA-C",
      "H_max": 15,
      "panic_rate": 0.1,
      "seed": 142,
      "hazard_seed": 1135,
      "elapsed_sec": 19.8
    },
    {
      "P_max": 13000,
      "n_impacted": 10004,
      "n_survival": 4778,
      "n_casualty": 754,
      "n_arrival": 2996,
      "n_active": 4472,
      "RI": 0.7695384615384615,
      "RS": 0.477608956417433,
      "RC": 0.07536985205917633,
      "RL": 0.44702119152339065,
      "community": "UVA-C",
      "H_max": 15,
      "panic_rate": 0.1,
      "seed": 242,
      "hazard_seed": 1135,
      "elapsed_sec": 19.3
    },
    {
      "P_max": 13000,
      "n_impacted": 10174,
      "n_survival": 4793,
      "n_casualty": 734,
      "n_arrival": 2826,
      "n_active": 4647,
      "RI": 0.7826153846153846,
      "RS": 0.47110281108708474,
      "RC": 0.07214468252408099,
      "RL": 0.4567525063888343,
      "community": "UVA-C",
      "H_max": 15,
      "panic_rate": 0.1,
      "seed": 342,
      "hazard_seed": 1135,
      "elapsed_sec": 19.9
    },
    {
      "P_max": 13000,
      "n_impacted": 10001,
      "n_survival": 4762,
      "n_casualty": 740,
      "n_arrival": 2999,
      "n_active": 4499,
      "RI": 0.7693076923076924,
      "RS": 0.47615238476152383,
      "RC": 0.073992600739926,
      "RL": 0.44985501449855014,
      "community": "UVA-C",
      "H_max": 15,
      "panic_rate": 0.1,
      "seed": 442,
      "hazard_seed": 1135,
      "elapsed_sec": 19.1
    },
    {
      "P_max": 13000,
      "n_impacted": 9998,
      "n_survival": 5085,
      "n_casualty": 635,
      "n_arrival": 3002,
      "n_active": 4278,
      "RI": 0.7690769230769231,
      "RS": 0.5086017203440688,
      "RC": 0.0635127025405081,
      "RL": 0.4278855771154231,
      "community": "UVA-C",
      "H_max": 15,
      "panic_rate": 0.1,
      "seed": 542,
      "hazard_seed": 1135,
      "elapsed_sec": 18.9
    },
    {
      "P_max": 13000,
      "n_impacted": 10195,
      "n_survival": 4700,
      "n_casualty": 736,
      "n_arrival": 2805,
      "n_active": 4759,
      "RI": 0.7842307692307692,
      "RS": 0.46101029916625796,
      "RC": 0.0721922511034821,
      "RL": 0.46679744973025994,
      "community": "UVA-C",
      "H_max": 15,
      "panic_rate": 0.1,
      "seed": 642,
      "hazard_seed": 1135,
      "elapsed_sec": 19.6
    },
    {
      "P_max": 13000,
      "n_impacted": 10132,
      "n_survival": 4900,
      "n_casualty": 736,
      "n_arrival": 2868,
      "n_active": 4496,
      "RI": 0.7793846153846153,
      "RS": 0.48361626529806556,
      "RC": 0.07264113699170943,
      "RL": 0.443742597710225,
      "community": "UVA-C",
      "H_max": 15,
      "panic_rate": 0.1,
      "seed": 742,
      "hazard_seed": 1135,
      "elapsed_sec": 19.3
    },
    {
      "P_max": 13000,
      "n_impacted": 10215,
      "n_survival": 4936,
      "n_casualty": 760,
      "n_arrival": 2785,
      "n_active": 4519,
      "RI": 0.7857692307692308,
      "RS": 0.483210964268233,
      "RC": 0.07440039158100832,
      "RL": 0.4423886441507587,
      "community": "UVA-C",
      "H_max": 15,
      "panic_rate": 0.1,
      "seed": 842,
      "hazard_seed": 1135,
      "elapsed_sec": 19.2
    },
    {
      "P_max": 13000,
      "n_impacted": 10063,
      "n_survival": 4599,
      "n_casualty": 771,
      "n_arrival": 2937,
      "n_active": 4693,
      "RI": 0.7740769230769231,
      "RS": 0.4570207691543277,
      "RC": 0.07661731094107126,
      "RL": 0.466361919904601,
      "community": "UVA-C",
      "H_max": 15,
      "panic_rate": 0.1,
      "seed": 942,
      "hazard_seed": 1135,
      "elapsed_sec": 19.6
    }
  ]
}