{
  "aggregated": {
    "community": "UVA-C",
    "P_max": 42000,
    "H_max": 15,
    "panic_rate": 0.1,
    "n_seeds": 10,
    "hazard_seed": 1135,
    "RI": 0.8578857142857144,
    "RI_std": 0.002749269125717529,
    "RS": 0.1604171109114862,
    "RS_std": 0.013437149187439013,
    "RC": 0.1106348528824305,
    "RC_std": 0.002289360260829018,
    "RL": 0.7289480362060832,
    "RL_std": 0.01265268540470835,
    "elapsed_sec": 762.4
  },
  "raw": [
    {
      "P_max": 42000,
      "n_impacted": 35971,
      "n_survival": 6332,
      "n_casualty": 3985,
      "n_arrival": 6029,
      "n_active": 25654,
      "RI": 0.856452380952381,
      "RS": 0.17603069139028663,
      "RC": 0.11078368685885852,
      "RL": 0.7131856217508549,
      "community": "UVA-C",
      "H_max": 15,
      "panic_rate": 0.1,
      "seed": 42,
      "hazard_seed": 1135,
      "elapsed_sec": 78.3
    },
    {
      "P_max": 42000,
      "n_impacted": 35988,
      "n_survival": 6066,
      "n_casualty": 3925,
      "n_arrival": 6012,
      "n_active": 25997,
      "RI": 0.8568571428571429,
      "RS": 0.1685561853951317,
      "RC": 0.10906413248860732,
      "RL": 0.722379682116261,
      "community": "UVA-C",
      "H_max": 15,
      "panic_rate": 0.1,
      "seed": 142,
      "hazard_seed": 1135,
      "elapsed_sec": 77.9
    },
    {
      "P_max": 42000,
      "n_impacted": 35998,
      "n_survival": 5239,
      "n_casualty": 4185,
      "n_arrival": 6002,
      "n_active": 26574,
      "RI": 0.8570952380952381,
      "RS": 0.14553586310350575,
      "RC": 0.11625645869214957,
      "RL": 0.7382076782043446,
      "community": "UVA-C",
      "H_max": 15,
      "panic_rate": 0.1,
      "seed": 242,
      "hazard_seed": 1135,
      "elapsed_sec": 78.3
    },
    {
      "P_max": 42000,
      "n_impacted": 35851,
      "n_survival": 5326,
      "n_casualty": 3957,
      "n_arrival": 6149,
      "n_active": 26568,
      "RI": 0.8535952380952381,
      "RS": 0.1485593149424005,
      "RC": 0.11037349027921117,
      "RL": 0.7410671947783883,
      "community": "UVA-C",
      "H_max": 15,
      "panic_rate": 0.1,
      "seed": 342,
      "hazard_seed": 1135,
      "elapsed_sec": 76.5
    },
    {
      "P_max": 42000,
      "n_impacted": 35952,
      "n_survival": 5772,
      "n_casualty": 4067,
      "n_arrival": 6048,
      "n_active": 26113,
      "RI": 0.856,
      "RS": 0.16054739652870495,
      "RC": 0.11312305295950156,
      "RL": 0.7263295505117935,
      "community": "UVA-C",
      "H_max": 15,
      "panic_rate": 0.1,
      "seed": 442,
      "hazard_seed": 1135,
      "elapsed_sec": 72.9
    },
    {
      "P_max": 42000,
      "n_impacted": 35988,
      "n_survival": 5375,
      "n_casualty": 3936,
      "n_arrival": 6012,
      "n_active": 26677,
      "RI": 0.8568571428571429,
      "RS": 0.14935534066911194,
      "RC": 0.10936978992997666,
      "RL": 0.7412748694009114,
      "community": "UVA-C",
      "H_max": 15,
      "panic_rate": 0.1,
      "seed": 542,
      "hazard_seed": 1135,
      "elapsed_sec": 83.8
    },
    {
      "P_max": 42000,
      "n_impacted": 35979,
      "n_survival": 5730,
      "n_casualty": 3988,
      "n_arrival": 6021,
      "n_active": 26261,
      "RI": 0.8566428571428572,
      "RS": 0.1592595680813808,
      "RC": 0.11084243586536591,
      "RL": 0.7298979960532533,
      "community": "UVA-C",
      "H_max": 15,
      "panic_rate": 0.1,
      "seed": 642,
      "hazard_seed": 1135,
      "elapsed_sec": 74.2
    },
    {
      "P_max": 42000,
      "n_impacted": 36239,
      "n_survival": 5165,
      "n_casualty": 3971,
      "n_arrival": 5761,
      "n_active": 27103,
      "RI": 0.8628333333333333,
      "RS": 0.14252600789205,
      "RC": 0.10957807886531085,
      "RL": 0.7478959132426392,
      "community": "UVA-C",
      "H_max": 15,
      "panic_rate": 0.1,
      "seed": 742,
      "hazard_seed": 1135,
      "elapsed_sec": 74.1
    },
    {
      "P_max": 42000,
      "n_impacted": 36175,
      "n_survival": 6090,
      "n_casualty": 3923,
      "n_arrival": 5825,
      "n_active": 26162,
      "RI": 0.8613095238095239,
      "RS": 0.16834830684174154,
      "RC": 0.10844505874222529,
      "RL": 0.7232066344160332,
      "community": "UVA-C",
      "H_max": 15,
      "panic_rate": 0.1,
      "seed": 842,
      "hazard_seed": 1135,
      "elapsed_sec": 73.9
    },
    {
      "P_max": 42000,
      "n_impacted": 36171,
      "n_survival": 6708,
      "n_casualty": 3925,
      "n_arrival": 5829,
      "n_active": 25538,
      "RI": 0.8612142857142857,
      "RS": 0.18545243427054822,
      "RC": 0.10851234414309806,
      "RL": 0.7060352215863537,
      "community": "UVA-C",
      "H_max": 15,
      "panic_rate": 0.1,
      "seed": 942,
      "hazard_seed": 1135,
      "elapsed_sec": 72.5
    }
  ]
}