{
  "aggregated": {
    "community": "UVA-C",
    "P_max": 1000,
    "H_max": 5,
    "panic_rate": 0.1,
    "n_seeds": 10,
    "hazard_seed": 1135,
    "RI": 0.03250000000000001,
    "RI_std": 0.005024937810560446,
    "RS": 0.975343137254902,
    "RS_std": 0.03222795972331665,
    "RC": 0.015049019607843139,
    "RC_std": 0.023305769268563925,
    "RL": 0.009607843137254901,
    "RL_std": 0.02094370991505008,
    "elapsed_sec": 37.9
  },
  "raw": [
    {
      "P_max": 1000,
      "n_impacted": 29,
      "n_survival": 29,
      "n_casualty": 0,
      "n_arrival": 971,
      "n_active": 0,
      "RI": 0.029,
      "RS": 1.0,
      "RC": 0.0,
      "RL": 0.0,
      "community": "UVA-C",
      "H_max": 5,
      "panic_rate": 0.1,
      "seed": 42,
      "hazard_seed": 1135,
      "elapsed_sec": 3.7
    },
    {
      "P_max": 1000,
      "n_impacted": 30,
      "n_survival": 30,
      "n_casualty": 0,
      "n_arrival": 970,
      "n_active": 0,
      "RI": 0.03,
      "RS": 1.0,
      "RC": 0.0,
      "RL": 0.0,
      "community": "UVA-C",
      "H_max": 5,
      "panic_rate": 0.1,
      "seed": 142,
      "hazard_seed": 1135,
      "elapsed_sec": 3.9
    },
    {
      "P_max": 1000,
      "n_impacted": 31,
      "n_survival": 31,
      "n_casualty": 0,
      "n_arrival": 969,
      "n_active": 0,
      "RI": 0.031,
      "RS": 1.0,
      "RC": 0.0,
      "RL": 0.0,
      "community": "UVA-C",
      "H_max": 5,
      "panic_rate": 0.1,
      "seed": 242,
      "hazard_seed": 1135,
      "elapsed_sec": 3.8
    },
    {
      "P_max": 1000,
      "n_impacted": 40,
      "n_survival": 38,
      "n_casualty": 2,
      "n_arrival": 960,
      "n_active": 0,
      "RI": 0.04,
      "RS": 0.95,
      "RC": 0.05,
      "RL": 0.0,
      "community": "UVA-C",
      "H_max": 5,
      "panic_rate": 0.1,
      "seed": 342,
      "hazard_seed": 1135,
      "elapsed_sec": 3.8
    },
    {
      "P_max": 1000,
      "n_impacted": 42,
      "n_survival": 42,
      "n_casualty": 0,
      "n_arrival": 958,
      "n_active": 0,
      "RI": 0.042,
      "RS": 1.0,
      "RC": 0.0,
      "RL": 0.0,
      "community": "UVA-C",
      "H_max": 5,
      "panic_rate": 0.1,
      "seed": 442,
      "hazard_seed": 1135,
      "elapsed_sec": 3.7
    },
    {
      "P_max": 1000,
      "n_impacted": 34,
      "n_survival": 31,
      "n_casualty": 2,
      "n_arrival": 966,
      "n_active": 1,
      "RI": 0.034,
      "RS": 0.9117647058823529,
      "RC": 0.058823529411764705,
      "RL": 0.029411764705882353,
      "community": "UVA-C",
      "H_max": 5,
      "panic_rate": 0.1,
      "seed": 542,
      "hazard_seed": 1135,
      "elapsed_sec": 3.8
    },
    {
      "P_max": 1000,
      "n_impacted": 24,
      "n_survival": 23,
      "n_casualty": 1,
      "n_arrival": 976,
      "n_active": 0,
      "RI": 0.024,
      "RS": 0.9583333333333334,
      "RC": 0.041666666666666664,
      "RL": 0.0,
      "community": "UVA-C",
      "H_max": 5,
      "panic_rate": 0.1,
      "seed": 642,
      "hazard_seed": 1135,
      "elapsed_sec": 3.8
    },
    {
      "P_max": 1000,
      "n_impacted": 31,
      "n_survival": 31,
      "n_casualty": 0,
      "n_arrival": 969,
      "n_active": 0,
      "RI": 0.031,
      "RS": 1.0,
      "RC": 0.0,
      "RL": 0.0,
      "community": "UVA-C",
      "H_max": 5,
      "panic_rate": 0.1,
      "seed": 742,
      "hazard_seed": 1135,
      "elapsed_sec": 3.7
    },
    {
      "P_max": 1000,
      "n_impacted": 34,
      "n_survival": 34,
      "n_casualty": 0,
      "n_arrival": 966,
      "n_active": 0,
      "RI": 0.034,
      "RS": 1.0,
      "RC": 0.0,
      "RL": 0.0,
      "community": "UVA-C",
      "H_max": 5,
      "panic_rate": 0.1,
      "seed": 842,
      "hazard_seed": 1135,
      "elapsed_sec": 3.9
    },
    {
      "P_max": 1000,
      "n_impacted": 30,
      "n_survival": 28,
      "n_casualty": 0,
      "n_arrival": 970,
      "n_active": 2,
      "RI": 0.03,
      "RS": 0.9333333333333333,
      "RC": 0.0,
      "RL": 0.06666666666666667,
      "community": "UVA-C",
      "H_max": 5,
      "panic_rate": 0.1,
      "seed": 942,
      "hazard_seed": 1135,
      "elapsed_sec": 3.8
    }
  ]
}