{
  "aggregated": {
    "community": "VT-B",
    "P_max": 5000,
    "H_max": 10,
    "panic_rate": 0.1,
    "n_seeds": 10,
    "hazard_seed": 1135,
    "RI": 0.5337799999999999,
    "RI_std": 0.00602425099078716,
    "RS": 0.9285086001329885,
    "RS_std": 0.012487186457115301,
    "RC": 0.02147157313733873,
    "RC_std": 0.003768281668457967,
    "RL": 0.05001982672967279,
    "RL_std": 0.009465162765093939,
    "elapsed_sec": 96.4
  },
  "raw": [
    {
      "P_max": 5000,
      "n_impacted": 2661,
      "n_survival": 2496,
      "n_casualty": 59,
      "n_arrival": 2339,
      "n_active": 106,
      "RI": 0.5322,
      "RS": 0.9379932356257046,
      "RC": 0.022172115745960164,
      "RL": 0.03983464862833521,
      "community": "VT-B",
      "H_max": 10,
      "panic_rate": 0.1,
      "seed": 42,
      "hazard_seed": 1135,
      "elapsed_sec": 9.4
    },
    {
      "P_max": 5000,
      "n_impacted": 2658,
      "n_survival": 2470,
      "n_casualty": 53,
      "n_arrival": 2342,
      "n_active": 135,
      "RI": 0.5316,
      "RS": 0.9292701279157262,
      "RC": 0.0199398043641836,
      "RL": 0.050790067720090294,
      "community": "VT-B",
      "H_max": 10,
      "panic_rate": 0.1,
      "seed": 142,
      "hazard_seed": 1135,
      "elapsed_sec": 9.5
    },
    {
      "P_max": 5000,
      "n_impacted": 2713,
      "n_survival": 2479,
      "n_casualty": 72,
      "n_arrival": 2287,
      "n_active": 162,
      "RI": 0.5426,
      "RS": 0.9137486177663103,
      "RC": 0.026538886841135274,
      "RL": 0.05971249539255437,
      "community": "VT-B",
      "H_max": 10,
      "panic_rate": 0.1,
      "seed": 242,
      "hazard_seed": 1135,
      "elapsed_sec": 10.3
    },
    {
      "P_max": 5000,
      "n_impacted": 2642,
      "n_survival": 2492,
      "n_casualty": 40,
      "n_arrival": 2358,
      "n_active": 110,
      "RI": 0.5284,
      "RS": 0.9432248296744891,
      "RC": 0.01514004542013626,
      "RL": 0.041635124905374715,
      "community": "VT-B",
      "H_max": 10,
      "panic_rate": 0.1,
      "seed": 342,
      "hazard_seed": 1135,
      "elapsed_sec": 9.4
    },
    {
      "P_max": 5000,
      "n_impacted": 2705,
      "n_survival": 2461,
      "n_casualty": 67,
      "n_arrival": 2295,
      "n_active": 177,
      "RI": 0.541,
      "RS": 0.9097966728280961,
      "RC": 0.02476894639556377,
      "RL": 0.06543438077634012,
      "community": "VT-B",
      "H_max": 10,
      "panic_rate": 0.1,
      "seed": 442,
      "hazard_seed": 1135,
      "elapsed_sec": 10.4
    },
    {
      "P_max": 5000,
      "n_impacted": 2618,
      "n_survival": 2464,
      "n_casualty": 43,
      "n_arrival": 2382,
      "n_active": 111,
      "RI": 0.5236,
      "RS": 0.9411764705882353,
      "RC": 0.016424751718869365,
      "RL": 0.04239877769289534,
      "community": "VT-B",
      "H_max": 10,
      "panic_rate": 0.1,
      "seed": 542,
      "hazard_seed": 1135,
      "elapsed_sec": 9.4
    },
    {
      "P_max": 5000,
      "n_impacted": 2688,
      "n_survival": 2491,
      "n_casualty": 68,
      "n_arrival": 2312,
      "n_active": 129,
      "RI": 0.5376,
      "RS": 0.9267113095238095,
      "RC": 0.025297619047619048,
      "RL": 0.04799107142857143,
      "community": "VT-B",
      "H_max": 10,
      "panic_rate": 0.1,
      "seed": 642,
      "hazard_seed": 1135,
      "elapsed_sec": 9.5
    },
    {
      "P_max": 5000,
      "n_impacted": 2689,
      "n_survival": 2445,
      "n_casualty": 68,
      "n_arrival": 2311,
      "n_active": 176,
      "RI": 0.5378,
      "RS": 0.9092599479360357,
      "RC": 0.02528821123094087,
      "RL": 0.06545184083302343,
      "community": "VT-B",
      "H_max": 10,
      "panic_rate": 0.1,
      "seed": 742,
      "hazard_seed": 1135,
      "elapsed_sec": 9.6
    },
    {
      "P_max": 5000,
      "n_impacted": 2632,
      "n_survival": 2461,
      "n_casualty": 53,
      "n_arrival": 2368,
      "n_active": 118,
      "RI": 0.5264,
      "RS": 0.9350303951367781,
      "RC": 0.02013677811550152,
      "RL": 0.044832826747720364,
      "community": "VT-B",
      "H_max": 10,
      "panic_rate": 0.1,
      "seed": 842,
      "hazard_seed": 1135,
      "elapsed_sec": 9.5
    },
    {
      "P_max": 5000,
      "n_impacted": 2683,
      "n_survival": 2519,
      "n_casualty": 51,
      "n_arrival": 2317,
      "n_active": 113,
      "RI": 0.5366,
      "RS": 0.9388743943347,
      "RC": 0.01900857249347745,
      "RL": 0.04211703317182259,
      "community": "VT-B",
      "H_max": 10,
      "panic_rate": 0.1,
      "seed": 942,
      "hazard_seed": 1135,
      "elapsed_sec": 9.4
    }
  ]
}